insuree_batch/__init__.py
insuree_batch/admin.py
insuree_batch/apps.py
insuree_batch/models.py
insuree_batch/schema.py
insuree_batch/services.py
insuree_batch/test_helpers.py
insuree_batch/tests.py
insuree_batch/urls.py
insuree_batch/views.py
insuree_batch/migrations/0001_initial.py
insuree_batch/migrations/0002_initial.py
insuree_batch/migrations/__init__.py
insuree_batch/templates/insuree_batch/batch_qr.html
openimis_be_insuree_batch-1.4.8.dist-info/LICENSE.md
openimis_be_insuree_batch-1.4.8.dist-info/METADATA
openimis_be_insuree_batch-1.4.8.dist-info/WHEEL
openimis_be_insuree_batch-1.4.8.dist-info/top_level.txt
openimis_be_insuree_batch-1.4.8.dist-info/RECORD
