Metadata-Version: 2.1
Name: openimis-be-insuree-batch
Version: 1.4.8
Summary: The openIMIS Backend Insuree Batch reference module.
Home-page: https://openimis.org/
Author: Eric Darchis
Author-email: edarchis@bluesquarehub.com
License: GNU AGPL v3
Classifier: Environment :: Web Environment
Classifier: Framework :: Django
Classifier: Framework :: Django :: 3.1
Classifier: Framework :: Django :: 3.2
Classifier: Intended Audience :: Developers
Classifier: License :: OSI Approved :: GNU Affero General Public License v3
Classifier: Operating System :: OS Independent
Classifier: Programming Language :: Python
Classifier: Programming Language :: Python :: 3.8
Classifier: Programming Language :: Python :: 3.9
Classifier: Programming Language :: Python :: 3.10
License-File: LICENSE.md
Requires-Dist: django
Requires-Dist: django-db-signals
Requires-Dist: djangorestframework
Requires-Dist: openimis-be-location
Requires-Dist: openimis-be-insuree
Requires-Dist: qrcode
